setup.cfg
setup.py
hyperop/__init__.py
hyperop/_version.py
hyperop/hyperop.py
hyperop.egg-info/PKG-INFO
hyperop.egg-info/SOURCES.txt
hyperop.egg-info/dependency_links.txt
hyperop.egg-info/top_level.txt