Metadata-Version: 1.1
Name: hyperop
Version: 1.1
Summary: Hyperoperators (succession, addition, multiplication, exponentiation, tetration and higher) in python.
Home-page: https://github.com/thoppe/python-hyperoperators
Author: Travis Hoppe
Author-email: travis.hoppe+hyperop@gmail.com
License: Creative Commons Attribution-ShareAlike 4.0 International License
Download-URL: https://github.com/thoppe/python-hyperoperators/tarball/1.1
Keywords: math,hyperoperators,uparrow,large-numbers
Platform: UNKNOWN
